{
  "generated_at": "2026-06-13T16:54:31.753806+02:00",
  "summary": {
    "odds_matches": 35,
    "ratings_players": 4732,
    "evaluated_matches": 34,
    "shadow_bets": 10,
    "no_bets": 24,
    "no_bet": 21,
    "player_2_insufficient_history": 7,
    "model_probability_below_threshold": 19,
    "probability_edge_below_threshold": 4,
    "ev_below_threshold": 7,
    "shadow_bet": 10,
    "player_1_insufficient_history": 3,
    "player_1_rating_missing": 2,
    "odds_below_threshold": 1,
    "missing_match_winner_market": 1,
    "player_2_rating_missing": 1
  },
  "settings": {
    "min_player_matches": 10,
    "min_model_probability": 0.55,
    "min_probability_edge": 0.03,
    "min_ev": 0.05,
    "min_odds": 1.5,
    "max_odds": 5.0,
    "overall_weight": 0.6,
    "surface_weight": 0.4,
    "surface_confidence_matches": 20
  },
  "top_shadow_picks": [
    {
      "pick_id": "12136425|match_winner|player_2",
      "event_key": 12136425,
      "date": "2026-06-13",
      "time": "18:40",
      "match": "A. Holmgren - M. Basing",
      "player_1": "A. Holmgren",
      "player_2": "M. Basing",
      "tournament": "Nottingham",
      "tournament_key": 2580,
      "round": "Nottingham - Semi-finals",
      "gender": "men",
      "tour_level": "challenger",
      "surface": "grass",
      "market": "match_winner",
      "pick_side": "player_2",
      "pick_player": "M. Basing",
      "odds": 3.05,
      "bookmaker": "Superbet",
      "median_odds": 3.05,
      "bookmakers_count": 1,
      "model_probability": 0.624607,
      "bookmaker_probability": 0.300459,
      "probability_edge": 0.324148,
      "fair_odds": 1.601,
      "ev": 0.905051,
      "decision": "SHADOW_BET",
      "confidence": "high",
      "reasons": [],
      "player_1_market": {
        "pick_side": "player_1",
        "pick_player": "A. Holmgren",
        "odds": 1.31,
        "bookmaker": "Superbet",
        "median_odds": 1.31,
        "bookmakers_count": 1,
        "model_probability": 0.375393,
        "bookmaker_probability": 0.699541,
        "probability_edge": -0.324148,
        "fair_odds": 2.664,
        "ev": -0.508235,
        "reasons": [
          "model_probability_below_threshold",
          "probability_edge_below_threshold",
          "ev_below_threshold",
          "odds_below_threshold"
        ]
      },
      "player_2_market": {
        "pick_side": "player_2",
        "pick_player": "M. Basing",
        "odds": 3.05,
        "bookmaker": "Superbet",
        "median_odds": 3.05,
        "bookmakers_count": 1,
        "model_probability": 0.624607,
        "bookmaker_probability": 0.300459,
        "probability_edge": 0.324148,
        "fair_odds": 1.601,
        "ev": 0.905051,
        "reasons": []
      },
      "rating_matches": {
        "player_1_status": "matched",
        "player_1_rating_name": "Holmgren A.",
        "player_1_matches": 69,
        "player_2_status": "matched",
        "player_2_rating_name": "Basing M.",
        "player_2_matches": 61
      },
      "elo_details": {
        "player_1_overall_elo": 1553.22,
        "player_2_overall_elo": 1646.451,
        "player_1_surface_elo": 1519.986,
        "player_2_surface_elo": 1499.263,
        "player_1_surface_matches": 2,
        "player_2_surface_matches": 8,
        "overall_p1_probability": 0.36896,
        "surface_p1_probability": 0.529787,
        "blended_p1_probability": 0.375393,
        "effective_overall_weight": 0.96,
        "effective_surface_weight": 0.04
      }
    },
    {
      "pick_id": "12136336|match_winner|player_2",
      "event_key": 12136336,
      "date": "2026-06-13",
      "time": "16:40",
      "match": "R. Carballes Baena - F. Forti",
      "player_1": "R. Carballes Baena",
      "player_2": "F. Forti",
      "tournament": "Cattolica (Italy) - Qualification",
      "tournament_key": 13955,
      "round": "Cattolica - Semi-finals",
      "gender": "men",
      "tour_level": "challenger",
      "surface": "clay",
      "market": "match_winner",
      "pick_side": "player_2",
      "pick_player": "F. Forti",
      "odds": 2.92,
      "bookmaker": "Pncl",
      "median_odds": 2.75,
      "bookmakers_count": 9,
      "model_probability": 0.644953,
      "bookmaker_probability": 0.337349,
      "probability_edge": 0.307604,
      "fair_odds": 1.551,
      "ev": 0.883263,
      "decision": "SHADOW_BET",
      "confidence": "high",
      "reasons": [],
      "player_1_market": {
        "pick_side": "player_1",
        "pick_player": "R. Carballes Baena",
        "odds": 1.44,
        "bookmaker": "Pncl",
        "median_odds": 1.4,
        "bookmakers_count": 9,
        "model_probability": 0.355047,
        "bookmaker_probability": 0.662651,
        "probability_edge": -0.307604,
        "fair_odds": 2.817,
        "ev": -0.488732,
        "reasons": [
          "model_probability_below_threshold",
          "probability_edge_below_threshold",
          "ev_below_threshold",
          "odds_below_threshold"
        ]
      },
      "player_2_market": {
        "pick_side": "player_2",
        "pick_player": "F. Forti",
        "odds": 2.92,
        "bookmaker": "Pncl",
        "median_odds": 2.75,
        "bookmakers_count": 9,
        "model_probability": 0.644953,
        "bookmaker_probability": 0.337349,
        "probability_edge": 0.307604,
        "fair_odds": 1.551,
        "ev": 0.883263,
        "reasons": []
      },
      "rating_matches": {
        "player_1_status": "matched",
        "player_1_rating_name": "Carballes Baena R.",
        "player_1_matches": 25,
        "player_2_status": "matched",
        "player_2_rating_name": "Forti F.",
        "player_2_matches": 109
      },
      "elo_details": {
        "player_1_overall_elo": 1539.689,
        "player_2_overall_elo": 1654.895,
        "player_1_surface_elo": 1544.323,
        "player_2_surface_elo": 1621.959,
        "player_1_surface_matches": 15,
        "player_2_surface_matches": 54,
        "overall_p1_probability": 0.340026,
        "surface_p1_probability": 0.390096,
        "blended_p1_probability": 0.355047,
        "effective_overall_weight": 0.7,
        "effective_surface_weight": 0.3
      }
    },
    {
      "pick_id": "12136412|match_winner|player_2",
      "event_key": 12136412,
      "date": "2026-06-13",
      "time": "19:50",
      "match": "Z. Sonmez - L. Tararudee",
      "player_1": "Z. Sonmez",
      "player_2": "L. Tararudee",
      "tournament": "Nottingham",
      "tournament_key": 2215,
      "round": "WTA Nottingham - Semi-finals",
      "gender": "women",
      "tour_level": "wta",
      "surface": "grass",
      "market": "match_winner",
      "pick_side": "player_2",
      "pick_player": "L. Tararudee",
      "odds": 2.6,
      "bookmaker": "WilliamHill",
      "median_odds": 2.47,
      "bookmakers_count": 7,
      "model_probability": 0.550932,
      "bookmaker_probability": 0.376263,
      "probability_edge": 0.174669,
      "fair_odds": 1.815,
      "ev": 0.432423,
      "decision": "SHADOW_BET",
      "confidence": "high",
      "reasons": [],
      "player_1_market": {
        "pick_side": "player_1",
        "pick_player": "Z. Sonmez",
        "odds": 1.5,
        "bookmaker": "BetVictor",
        "median_odds": 1.49,
        "bookmakers_count": 7,
        "model_probability": 0.449068,
        "bookmaker_probability": 0.623737,
        "probability_edge": -0.174669,
        "fair_odds": 2.227,
        "ev": -0.326398,
        "reasons": [
          "model_probability_below_threshold",
          "probability_edge_below_threshold",
          "ev_below_threshold"
        ]
      },
      "player_2_market": {
        "pick_side": "player_2",
        "pick_player": "L. Tararudee",
        "odds": 2.6,
        "bookmaker": "WilliamHill",
        "median_odds": 2.47,
        "bookmakers_count": 7,
        "model_probability": 0.550932,
        "bookmaker_probability": 0.376263,
        "probability_edge": 0.174669,
        "fair_odds": 1.815,
        "ev": 0.432423,
        "reasons": []
      },
      "rating_matches": {
        "player_1_status": "matched",
        "player_1_rating_name": "Sonmez Z.",
        "player_1_matches": 14,
        "player_2_status": "matched",
        "player_2_rating_name": "Tararudee L.",
        "player_2_matches": 14
      },
      "elo_details": {
        "player_1_overall_elo": 1519.727,
        "player_2_overall_elo": 1555.237,
        "player_1_surface_elo": 1474.279,
        "player_2_surface_elo": 1510.0,
        "player_1_surface_matches": 3,
        "player_2_surface_matches": 1,
        "overall_p1_probability": 0.449074,
        "surface_p1_probability": 0.448774,
        "blended_p1_probability": 0.449068,
        "effective_overall_weight": 0.98,
        "effective_surface_weight": 0.02
      }
    },
    {
      "pick_id": "12136388|match_winner|player_1",
      "event_key": 12136388,
      "date": "2026-06-13",
      "time": "16:35",
      "match": "D. Prizmic - R. Hijikata",
      "player_1": "D. Prizmic",
      "player_2": "R. Hijikata",
      "tournament": "London",
      "tournament_key": 2042,
      "round": "ATP London - Semi-finals",
      "gender": "men",
      "tour_level": "atp",
      "surface": "unknown",
      "market": "match_winner",
      "pick_side": "player_1",
      "pick_player": "D. Prizmic",
      "odds": 1.87,
      "bookmaker": "Pncl",
      "median_odds": 1.84,
      "bookmakers_count": 6,
      "model_probability": 0.720776,
      "bookmaker_probability": 0.512583,
      "probability_edge": 0.208193,
      "fair_odds": 1.387,
      "ev": 0.347851,
      "decision": "SHADOW_BET",
      "confidence": "high",
      "reasons": [],
      "player_1_market": {
        "pick_side": "player_1",
        "pick_player": "D. Prizmic",
        "odds": 1.87,
        "bookmaker": "Pncl",
        "median_odds": 1.84,
        "bookmakers_count": 6,
        "model_probability": 0.720776,
        "bookmaker_probability": 0.512583,
        "probability_edge": 0.208193,
        "fair_odds": 1.387,
        "ev": 0.347851,
        "reasons": []
      },
      "player_2_market": {
        "pick_side": "player_2",
        "pick_player": "R. Hijikata",
        "odds": 2.0,
        "bookmaker": "bet365",
        "median_odds": 1.935,
        "bookmakers_count": 6,
        "model_probability": 0.279224,
        "bookmaker_probability": 0.487417,
        "probability_edge": -0.208193,
        "fair_odds": 3.581,
        "ev": -0.441552,
        "reasons": [
          "model_probability_below_threshold",
          "probability_edge_below_threshold",
          "ev_below_threshold"
        ]
      },
      "rating_matches": {
        "player_1_status": "matched",
        "player_1_rating_name": "Prižmić D.",
        "player_1_matches": 14,
        "player_2_status": "matched",
        "player_2_rating_name": "Hijikata R.",
        "player_2_matches": 26
      },
      "elo_details": {
        "player_1_overall_elo": 1604.091,
        "player_2_overall_elo": 1439.352,
        "player_1_surface_elo": 1604.091,
        "player_2_surface_elo": 1439.352,
        "player_1_surface_matches": 0,
        "player_2_surface_matches": 0,
        "overall_p1_probability": 0.720776,
        "surface_p1_probability": 0.720776,
        "blended_p1_probability": 0.720776,
        "effective_overall_weight": 1.0,
        "effective_surface_weight": 0.0
      }
    },
    {
      "pick_id": "12136474|match_winner|player_1",
      "event_key": 12136474,
      "date": "2026-06-13",
      "time": "16:30",
      "match": "V. Orlov - S. Perez Contri",
      "player_1": "V. Orlov",
      "player_2": "S. Perez Contri",
      "tournament": "M25 Kiseljak",
      "tournament_key": 4114,
      "round": "M25 Kiseljak - Semi-finals",
      "gender": "men",
      "tour_level": "itf",
      "surface": "unknown",
      "market": "match_winner",
      "pick_side": "player_1",
      "pick_player": "V. Orlov",
      "odds": 2.25,
      "bookmaker": "Betfair",
      "median_odds": 2.25,
      "bookmakers_count": 1,
      "model_probability": 0.590928,
      "bookmaker_probability": 0.410995,
      "probability_edge": 0.179933,
      "fair_odds": 1.692,
      "ev": 0.329588,
      "decision": "SHADOW_BET",
      "confidence": "high",
      "reasons": [],
      "player_1_market": {
        "pick_side": "player_1",
        "pick_player": "V. Orlov",
        "odds": 2.25,
        "bookmaker": "Betfair",
        "median_odds": 2.25,
        "bookmakers_count": 1,
        "model_probability": 0.590928,
        "bookmaker_probability": 0.410995,
        "probability_edge": 0.179933,
        "fair_odds": 1.692,
        "ev": 0.329588,
        "reasons": []
      },
      "player_2_market": {
        "pick_side": "player_2",
        "pick_player": "S. Perez Contri",
        "odds": 1.57,
        "bookmaker": "Betfair",
        "median_odds": 1.57,
        "bookmakers_count": 1,
        "model_probability": 0.409072,
        "bookmaker_probability": 0.589005,
        "probability_edge": -0.179933,
        "fair_odds": 2.445,
        "ev": -0.357757,
        "reasons": [
          "model_probability_below_threshold",
          "probability_edge_below_threshold",
          "ev_below_threshold"
        ]
      },
      "rating_matches": {
        "player_1_status": "matched",
        "player_1_rating_name": "Orlov V.",
        "player_1_matches": 108,
        "player_2_status": "matched",
        "player_2_rating_name": "Perez Contri S.",
        "player_2_matches": 11
      },
      "elo_details": {
        "player_1_overall_elo": 1576.423,
        "player_2_overall_elo": 1512.529,
        "player_1_surface_elo": 1576.423,
        "player_2_surface_elo": 1512.529,
        "player_1_surface_matches": 0,
        "player_2_surface_matches": 0,
        "overall_p1_probability": 0.590928,
        "surface_p1_probability": 0.590928,
        "blended_p1_probability": 0.590928,
        "effective_overall_weight": 1.0,
        "effective_surface_weight": 0.0
      }
    },
    {
      "pick_id": "12136348|match_winner|player_2",
      "event_key": 12136348,
      "date": "2026-06-13",
      "time": "17:00",
      "match": "S. Gorzny - E. Aguiard",
      "player_1": "S. Gorzny",
      "player_2": "E. Aguiard",
      "tournament": "M25 Wichita, KS",
      "tournament_key": 4195,
      "round": "M25 Wichita, KS - Semi-finals",
      "gender": "men",
      "tour_level": "itf",
      "surface": "unknown",
      "market": "match_winner",
      "pick_side": "player_2",
      "pick_player": "E. Aguiard",
      "odds": 2.08,
      "bookmaker": "1xBet",
      "median_odds": 2.08,
      "bookmakers_count": 1,
      "model_probability": 0.614627,
      "bookmaker_probability": 0.445333,
      "probability_edge": 0.169294,
      "fair_odds": 1.627,
      "ev": 0.278424,
      "decision": "SHADOW_BET",
      "confidence": "high",
      "reasons": [],
      "player_1_market": {
        "pick_side": "player_1",
        "pick_player": "S. Gorzny",
        "odds": 1.67,
        "bookmaker": "1xBet",
        "median_odds": 1.67,
        "bookmakers_count": 1,
        "model_probability": 0.385373,
        "bookmaker_probability": 0.554667,
        "probability_edge": -0.169294,
        "fair_odds": 2.595,
        "ev": -0.356427,
        "reasons": [
          "model_probability_below_threshold",
          "probability_edge_below_threshold",
          "ev_below_threshold"
        ]
      },
      "player_2_market": {
        "pick_side": "player_2",
        "pick_player": "E. Aguiard",
        "odds": 2.08,
        "bookmaker": "1xBet",
        "median_odds": 2.08,
        "bookmakers_count": 1,
        "model_probability": 0.614627,
        "bookmaker_probability": 0.445333,
        "probability_edge": 0.169294,
        "fair_odds": 1.627,
        "ev": 0.278424,
        "reasons": []
      },
      "rating_matches": {
        "player_1_status": "matched",
        "player_1_rating_name": "Gorzny S.",
        "player_1_matches": 35,
        "player_2_status": "matched",
        "player_2_rating_name": "Aguiard E.",
        "player_2_matches": 56
      },
      "elo_details": {
        "player_1_overall_elo": 1520.678,
        "player_2_overall_elo": 1601.77,
        "player_1_surface_elo": 1520.678,
        "player_2_surface_elo": 1601.77,
        "player_1_surface_matches": 0,
        "player_2_surface_matches": 0,
        "overall_p1_probability": 0.385373,
        "surface_p1_probability": 0.385373,
        "blended_p1_probability": 0.385373,
        "effective_overall_weight": 1.0,
        "effective_surface_weight": 0.0
      }
    },
    {
      "pick_id": "12136338|match_winner|player_2",
      "event_key": 12136338,
      "date": "2026-06-13",
      "time": "16:50",
      "match": "D. E. Galan - F. Balshaw",
      "player_1": "D. E. Galan",
      "player_2": "F. Balshaw",
      "tournament": "Lyon",
      "tournament_key": 2389,
      "round": "Lyon - Semi-finals",
      "gender": "men",
      "tour_level": "challenger",
      "surface": "clay",
      "market": "match_winner",
      "pick_side": "player_2",
      "pick_player": "F. Balshaw",
      "odds": 1.77,
      "bookmaker": "Pncl",
      "median_odds": 1.71,
      "bookmakers_count": 10,
      "model_probability": 0.719247,
      "bookmaker_probability": 0.544,
      "probability_edge": 0.175247,
      "fair_odds": 1.39,
      "ev": 0.273068,
      "decision": "SHADOW_BET",
      "confidence": "high",
      "reasons": [],
      "player_1_market": {
        "pick_side": "player_1",
        "pick_player": "D. E. Galan",
        "odds": 2.13,
        "bookmaker": "Pncl",
        "median_odds": 2.04,
        "bookmakers_count": 10,
        "model_probability": 0.280753,
        "bookmaker_probability": 0.456,
        "probability_edge": -0.175247,
        "fair_odds": 3.562,
        "ev": -0.401997,
        "reasons": [
          "model_probability_below_threshold",
          "probability_edge_below_threshold",
          "ev_below_threshold"
        ]
      },
      "player_2_market": {
        "pick_side": "player_2",
        "pick_player": "F. Balshaw",
        "odds": 1.77,
        "bookmaker": "Pncl",
        "median_odds": 1.71,
        "bookmakers_count": 10,
        "model_probability": 0.719247,
        "bookmaker_probability": 0.544,
        "probability_edge": 0.175247,
        "fair_odds": 1.39,
        "ev": 0.273068,
        "reasons": []
      },
      "rating_matches": {
        "player_1_status": "matched",
        "player_1_rating_name": "Galan D. E.",
        "player_1_matches": 106,
        "player_2_status": "matched",
        "player_2_rating_name": "Balshaw F.",
        "player_2_matches": 97
      },
      "elo_details": {
        "player_1_overall_elo": 1518.375,
        "player_2_overall_elo": 1685.874,
        "player_1_surface_elo": 1514.335,
        "player_2_surface_elo": 1671.718,
        "player_1_surface_matches": 54,
        "player_2_surface_matches": 51,
        "overall_p1_probability": 0.276038,
        "surface_p1_probability": 0.287825,
        "blended_p1_probability": 0.280753,
        "effective_overall_weight": 0.6,
        "effective_surface_weight": 0.4
      }
    },
    {
      "pick_id": "12136395|match_winner|player_1",
      "event_key": 12136395,
      "date": "2026-06-13",
      "time": "16:30",
      "match": "D. Parry - E. Seidel",
      "player_1": "D. Parry",
      "player_2": "E. Seidel",
      "tournament": "Berlin",
      "tournament_key": 3183,
      "round": "WTA Berlin - Semi-finals",
      "gender": "women",
      "tour_level": "wta",
      "surface": "grass",
      "market": "match_winner",
      "pick_side": "player_1",
      "pick_player": "D. Parry",
      "odds": 1.73,
      "bookmaker": "WilliamHill",
      "median_odds": 1.665,
      "bookmakers_count": 8,
      "model_probability": 0.66069,
      "bookmaker_probability": 0.55894,
      "probability_edge": 0.10175,
      "fair_odds": 1.514,
      "ev": 0.142994,
      "decision": "SHADOW_BET",
      "confidence": "high",
      "reasons": [],
      "player_1_market": {
        "pick_side": "player_1",
        "pick_player": "D. Parry",
        "odds": 1.73,
        "bookmaker": "WilliamHill",
        "median_odds": 1.665,
        "bookmakers_count": 8,
        "model_probability": 0.66069,
        "bookmaker_probability": 0.55894,
        "probability_edge": 0.10175,
        "fair_odds": 1.514,
        "ev": 0.142994,
        "reasons": []
      },
      "player_2_market": {
        "pick_side": "player_2",
        "pick_player": "E. Seidel",
        "odds": 2.24,
        "bookmaker": "Pncl",
        "median_odds": 2.11,
        "bookmakers_count": 8,
        "model_probability": 0.33931,
        "bookmaker_probability": 0.44106,
        "probability_edge": -0.10175,
        "fair_odds": 2.947,
        "ev": -0.239945,
        "reasons": [
          "model_probability_below_threshold",
          "probability_edge_below_threshold",
          "ev_below_threshold"
        ]
      },
      "rating_matches": {
        "player_1_status": "matched",
        "player_1_rating_name": "Parry D.",
        "player_1_matches": 11,
        "player_2_status": "matched",
        "player_2_rating_name": "Seidel E.",
        "player_2_matches": 26
      },
      "elo_details": {
        "player_1_overall_elo": 1576.657,
        "player_2_overall_elo": 1459.041,
        "player_1_surface_elo": 1520.063,
        "player_2_surface_elo": 1489.722,
        "player_1_surface_matches": 2,
        "player_2_surface_matches": 1,
        "overall_p1_probability": 0.66308,
        "surface_p1_probability": 0.543554,
        "blended_p1_probability": 0.66069,
        "effective_overall_weight": 0.98,
        "effective_surface_weight": 0.02
      }
    },
    {
      "pick_id": "12136398|match_winner|player_1",
      "event_key": 12136398,
      "date": "2026-06-13",
      "time": "18:20",
      "match": "P. Kudermetova - S. Kraus",
      "player_1": "P. Kudermetova",
      "player_2": "S. Kraus",
      "tournament": "Berlin",
      "tournament_key": 3183,
      "round": "WTA Berlin - Semi-finals",
      "gender": "women",
      "tour_level": "wta",
      "surface": "grass",
      "market": "match_winner",
      "pick_side": "player_1",
      "pick_player": "P. Kudermetova",
      "odds": 2.0,
      "bookmaker": "WilliamHill",
      "median_odds": 1.91,
      "bookmakers_count": 7,
      "model_probability": 0.562057,
      "bookmaker_probability": 0.485175,
      "probability_edge": 0.076882,
      "fair_odds": 1.779,
      "ev": 0.124114,
      "decision": "SHADOW_BET",
      "confidence": "high",
      "reasons": [],
      "player_1_market": {
        "pick_side": "player_1",
        "pick_player": "P. Kudermetova",
        "odds": 2.0,
        "bookmaker": "WilliamHill",
        "median_odds": 1.91,
        "bookmakers_count": 7,
        "model_probability": 0.562057,
        "bookmaker_probability": 0.485175,
        "probability_edge": 0.076882,
        "fair_odds": 1.779,
        "ev": 0.124114,
        "reasons": []
      },
      "player_2_market": {
        "pick_side": "player_2",
        "pick_player": "S. Kraus",
        "odds": 1.82,
        "bookmaker": "Superbet",
        "median_odds": 1.8,
        "bookmakers_count": 7,
        "model_probability": 0.437943,
        "bookmaker_probability": 0.514825,
        "probability_edge": -0.076882,
        "fair_odds": 2.283,
        "ev": -0.202943,
        "reasons": [
          "model_probability_below_threshold",
          "probability_edge_below_threshold",
          "ev_below_threshold"
        ]
      },
      "rating_matches": {
        "player_1_status": "matched",
        "player_1_rating_name": "Kudermetova P.",
        "player_1_matches": 49,
        "player_2_status": "matched",
        "player_2_rating_name": "Kraus S.",
        "player_2_matches": 17
      },
      "elo_details": {
        "player_1_overall_elo": 1594.315,
        "player_2_overall_elo": 1550.97,
        "player_1_surface_elo": 1491.076,
        "player_2_surface_elo": 1500.0,
        "player_1_surface_matches": 1,
        "player_2_surface_matches": 0,
        "overall_p1_probability": 0.562057,
        "surface_p1_probability": 0.48716,
        "blended_p1_probability": 0.562057,
        "effective_overall_weight": 1.0,
        "effective_surface_weight": 0.0
      }
    },
    {
      "pick_id": "12136397|match_winner|player_1",
      "event_key": 12136397,
      "date": "2026-06-13",
      "time": "16:55",
      "match": "M. Timofeeva - R. Zarazua",
      "player_1": "M. Timofeeva",
      "player_2": "R. Zarazua",
      "tournament": "Berlin",
      "tournament_key": 3183,
      "round": "WTA Berlin - Semi-finals",
      "gender": "women",
      "tour_level": "wta",
      "surface": "grass",
      "market": "match_winner",
      "pick_side": "player_1",
      "pick_player": "M. Timofeeva",
      "odds": 1.68,
      "bookmaker": "Sbo",
      "median_odds": 1.615,
      "bookmakers_count": 8,
      "model_probability": 0.627279,
      "bookmaker_probability": 0.576671,
      "probability_edge": 0.050608,
      "fair_odds": 1.594,
      "ev": 0.053829,
      "decision": "SHADOW_BET",
      "confidence": "medium",
      "reasons": [],
      "player_1_market": {
        "pick_side": "player_1",
        "pick_player": "M. Timofeeva",
        "odds": 1.68,
        "bookmaker": "Sbo",
        "median_odds": 1.615,
        "bookmakers_count": 8,
        "model_probability": 0.627279,
        "bookmaker_probability": 0.576671,
        "probability_edge": 0.050608,
        "fair_odds": 1.594,
        "ev": 0.053829,
        "reasons": []
      },
      "player_2_market": {
        "pick_side": "player_2",
        "pick_player": "R. Zarazua",
        "odds": 2.3,
        "bookmaker": "WilliamHill",
        "median_odds": 2.2,
        "bookmakers_count": 8,
        "model_probability": 0.372721,
        "bookmaker_probability": 0.423329,
        "probability_edge": -0.050608,
        "fair_odds": 2.683,
        "ev": -0.142742,
        "reasons": [
          "model_probability_below_threshold",
          "probability_edge_below_threshold",
          "ev_below_threshold"
        ]
      },
      "rating_matches": {
        "player_1_status": "matched",
        "player_1_rating_name": "Timofeeva M.",
        "player_1_matches": 16,
        "player_2_status": "matched",
        "player_2_rating_name": "Zarazua R.",
        "player_2_matches": 21
      },
      "elo_details": {
        "player_1_overall_elo": 1582.159,
        "player_2_overall_elo": 1491.728,
        "player_1_surface_elo": 1500.0,
        "player_2_surface_elo": 1502.108,
        "player_1_surface_matches": 0,
        "player_2_surface_matches": 2,
        "overall_p1_probability": 0.627279,
        "surface_p1_probability": 0.496966,
        "blended_p1_probability": 0.627279,
        "effective_overall_weight": 1.0,
        "effective_surface_weight": 0.0
      }
    }
  ]
}
