{
  "generated_at": "2026-06-10T18:27:26.522792+02:00",
  "summary": {
    "odds_matches": 84,
    "ratings_players": 4148,
    "evaluated_matches": 84,
    "shadow_bets": 4,
    "no_bets": 80,
    "no_bet": 49,
    "player_2_insufficient_history": 36,
    "model_probability_below_threshold": 44,
    "odds_above_threshold": 8,
    "player_1_insufficient_history": 34,
    "player_2_rating_missing": 16,
    "shadow_bet": 4,
    "ev_below_threshold": 10,
    "probability_edge_below_threshold": 7,
    "player_1_rating_missing": 19
  },
  "settings": {
    "min_player_matches": 10,
    "min_model_probability": 0.55,
    "min_probability_edge": 0.03,
    "min_ev": 0.05,
    "min_odds": 1.5,
    "max_odds": 5.0,
    "overall_weight": 0.6,
    "surface_weight": 0.4,
    "surface_confidence_matches": 20
  },
  "top_shadow_picks": [
    {
      "pick_id": "12134775|match_winner|player_1",
      "event_key": 12134775,
      "date": "2026-06-10",
      "time": "18:15",
      "match": "H. Rocha - C. Broom",
      "player_1": "H. Rocha",
      "player_2": "C. Broom",
      "tournament": "Ilkley",
      "tournament_key": 2507,
      "round": "Ilkley - 1/16-finals",
      "gender": "men",
      "tour_level": "challenger",
      "surface": "grass",
      "market": "match_winner",
      "pick_side": "player_1",
      "pick_player": "H. Rocha",
      "odds": 2.51,
      "bookmaker": "Pncl",
      "median_odds": 2.4,
      "bookmakers_count": 11,
      "model_probability": 0.618242,
      "bookmaker_probability": 0.389313,
      "probability_edge": 0.228929,
      "fair_odds": 1.617,
      "ev": 0.551787,
      "decision": "SHADOW_BET",
      "confidence": "high",
      "reasons": [],
      "player_1_market": {
        "pick_side": "player_1",
        "pick_player": "H. Rocha",
        "odds": 2.51,
        "bookmaker": "Pncl",
        "median_odds": 2.4,
        "bookmakers_count": 11,
        "model_probability": 0.618242,
        "bookmaker_probability": 0.389313,
        "probability_edge": 0.228929,
        "fair_odds": 1.617,
        "ev": 0.551787,
        "reasons": []
      },
      "player_2_market": {
        "pick_side": "player_2",
        "pick_player": "C. Broom",
        "odds": 1.58,
        "bookmaker": "Superbet",
        "median_odds": 1.53,
        "bookmakers_count": 11,
        "model_probability": 0.381758,
        "bookmaker_probability": 0.610687,
        "probability_edge": -0.228929,
        "fair_odds": 2.619,
        "ev": -0.396822,
        "reasons": [
          "model_probability_below_threshold",
          "probability_edge_below_threshold",
          "ev_below_threshold"
        ]
      },
      "rating_matches": {
        "player_1_status": "matched",
        "player_1_rating_name": "Rocha H.",
        "player_1_matches": 107,
        "player_2_status": "matched",
        "player_2_rating_name": "Broom C.",
        "player_2_matches": 31
      },
      "elo_details": {
        "player_1_overall_elo": 1618.661,
        "player_2_overall_elo": 1534.913,
        "player_1_surface_elo": 1500.0,
        "player_2_surface_elo": 1510.441,
        "player_1_surface_matches": 0,
        "player_2_surface_matches": 3,
        "overall_p1_probability": 0.618242,
        "surface_p1_probability": 0.484979,
        "blended_p1_probability": 0.618242,
        "effective_overall_weight": 1.0,
        "effective_surface_weight": 0.0
      }
    },
    {
      "pick_id": "12135367|match_winner|player_2",
      "event_key": 12135367,
      "date": "2026-06-10",
      "time": "18:30",
      "match": "M. Bouzkova - D. Vekic",
      "player_1": "M. Bouzkova",
      "player_2": "D. Vekic",
      "tournament": "London",
      "tournament_key": 12571,
      "round": "WTA London - 1/8-finals",
      "gender": "women",
      "tour_level": "wta",
      "surface": "grass",
      "market": "match_winner",
      "pick_side": "player_2",
      "pick_player": "D. Vekic",
      "odds": 2.43,
      "bookmaker": "Pncl",
      "median_odds": 2.37,
      "bookmakers_count": 12,
      "model_probability": 0.595261,
      "bookmaker_probability": 0.4,
      "probability_edge": 0.195261,
      "fair_odds": 1.68,
      "ev": 0.446483,
      "decision": "SHADOW_BET",
      "confidence": "high",
      "reasons": [],
      "player_1_market": {
        "pick_side": "player_1",
        "pick_player": "M. Bouzkova",
        "odds": 1.62,
        "bookmaker": "Betfair",
        "median_odds": 1.58,
        "bookmakers_count": 12,
        "model_probability": 0.404739,
        "bookmaker_probability": 0.6,
        "probability_edge": -0.195261,
        "fair_odds": 2.471,
        "ev": -0.344322,
        "reasons": [
          "model_probability_below_threshold",
          "probability_edge_below_threshold",
          "ev_below_threshold"
        ]
      },
      "player_2_market": {
        "pick_side": "player_2",
        "pick_player": "D. Vekic",
        "odds": 2.43,
        "bookmaker": "Pncl",
        "median_odds": 2.37,
        "bookmakers_count": 12,
        "model_probability": 0.595261,
        "bookmaker_probability": 0.4,
        "probability_edge": 0.195261,
        "fair_odds": 1.68,
        "ev": 0.446483,
        "reasons": []
      },
      "rating_matches": {
        "player_1_status": "matched",
        "player_1_rating_name": "Bouzkova M.",
        "player_1_matches": 19,
        "player_2_status": "matched",
        "player_2_rating_name": "Vekić D.",
        "player_2_matches": 149
      },
      "elo_details": {
        "player_1_overall_elo": 1511.115,
        "player_2_overall_elo": 1578.022,
        "player_1_surface_elo": 1488.964,
        "player_2_surface_elo": 1557.634,
        "player_1_surface_matches": 3,
        "player_2_surface_matches": 49,
        "overall_p1_probability": 0.404886,
        "surface_p1_probability": 0.402443,
        "blended_p1_probability": 0.404739,
        "effective_overall_weight": 0.94,
        "effective_surface_weight": 0.06
      }
    },
    {
      "pick_id": "12135484|match_winner|player_1",
      "event_key": 12135484,
      "date": "2026-06-10",
      "time": "19:00",
      "match": "V. Jimenez Kasintseva - V. Lepchenko",
      "player_1": "V. Jimenez Kasintseva",
      "player_2": "V. Lepchenko",
      "tournament": "Modena (Italy) - Qualification",
      "tournament_key": 13956,
      "round": "Modena - 1/8-finals",
      "gender": "women",
      "tour_level": "challenger",
      "surface": "clay",
      "market": "match_winner",
      "pick_side": "player_1",
      "pick_player": "V. Jimenez Kasintseva",
      "odds": 1.94,
      "bookmaker": "Pncl",
      "median_odds": 1.88,
      "bookmakers_count": 5,
      "model_probability": 0.564185,
      "bookmaker_probability": 0.498667,
      "probability_edge": 0.065518,
      "fair_odds": 1.772,
      "ev": 0.094519,
      "decision": "SHADOW_BET",
      "confidence": "medium",
      "reasons": [],
      "player_1_market": {
        "pick_side": "player_1",
        "pick_player": "V. Jimenez Kasintseva",
        "odds": 1.94,
        "bookmaker": "Pncl",
        "median_odds": 1.88,
        "bookmakers_count": 5,
        "model_probability": 0.564185,
        "bookmaker_probability": 0.498667,
        "probability_edge": 0.065518,
        "fair_odds": 1.772,
        "ev": 0.094519,
        "reasons": []
      },
      "player_2_market": {
        "pick_side": "player_2",
        "pick_player": "V. Lepchenko",
        "odds": 1.9,
        "bookmaker": "Betano",
        "median_odds": 1.87,
        "bookmakers_count": 5,
        "model_probability": 0.435815,
        "bookmaker_probability": 0.501333,
        "probability_edge": -0.065518,
        "fair_odds": 2.295,
        "ev": -0.171951,
        "reasons": [
          "model_probability_below_threshold",
          "probability_edge_below_threshold",
          "ev_below_threshold"
        ]
      },
      "rating_matches": {
        "player_1_status": "matched",
        "player_1_rating_name": "Jimenez Kasintseva V.",
        "player_1_matches": 15,
        "player_2_status": "matched",
        "player_2_rating_name": "Lepchenko V.",
        "player_2_matches": 55
      },
      "elo_details": {
        "player_1_overall_elo": 1551.176,
        "player_2_overall_elo": 1504.068,
        "player_1_surface_elo": 1521.997,
        "player_2_surface_elo": 1502.922,
        "player_1_surface_matches": 4,
        "player_2_surface_matches": 24,
        "overall_p1_probability": 0.567381,
        "surface_p1_probability": 0.527424,
        "blended_p1_probability": 0.564185,
        "effective_overall_weight": 0.92,
        "effective_surface_weight": 0.08
      }
    },
    {
      "pick_id": "12135020|match_winner|player_1",
      "event_key": 12135020,
      "date": "2026-06-10",
      "time": "19:10",
      "match": "E. Aguiard - A. Soriano Barrera",
      "player_1": "E. Aguiard",
      "player_2": "A. Soriano Barrera",
      "tournament": "M25 Wichita, KS",
      "tournament_key": 4195,
      "round": "M25 Wichita, KS - 1/16-finals",
      "gender": "men",
      "tour_level": "itf",
      "surface": "unknown",
      "market": "match_winner",
      "pick_side": "player_1",
      "pick_player": "E. Aguiard",
      "odds": 1.79,
      "bookmaker": "Pncl",
      "median_odds": 1.74,
      "bookmakers_count": 6,
      "model_probability": 0.605881,
      "bookmaker_probability": 0.52973,
      "probability_edge": 0.076151,
      "fair_odds": 1.65,
      "ev": 0.084527,
      "decision": "SHADOW_BET",
      "confidence": "medium",
      "reasons": [],
      "player_1_market": {
        "pick_side": "player_1",
        "pick_player": "E. Aguiard",
        "odds": 1.79,
        "bookmaker": "Pncl",
        "median_odds": 1.74,
        "bookmakers_count": 6,
        "model_probability": 0.605881,
        "bookmaker_probability": 0.52973,
        "probability_edge": 0.076151,
        "fair_odds": 1.65,
        "ev": 0.084527,
        "reasons": []
      },
      "player_2_market": {
        "pick_side": "player_2",
        "pick_player": "A. Soriano Barrera",
        "odds": 2.0,
        "bookmaker": "Betfair",
        "median_odds": 1.96,
        "bookmakers_count": 6,
        "model_probability": 0.394119,
        "bookmaker_probability": 0.47027,
        "probability_edge": -0.076151,
        "fair_odds": 2.537,
        "ev": -0.211762,
        "reasons": [
          "model_probability_below_threshold",
          "probability_edge_below_threshold",
          "ev_below_threshold"
        ]
      },
      "rating_matches": {
        "player_1_status": "matched",
        "player_1_rating_name": "Aguiard E.",
        "player_1_matches": 53,
        "player_2_status": "matched",
        "player_2_rating_name": "Soriano Barrera A.",
        "player_2_matches": 51
      },
      "elo_details": {
        "player_1_overall_elo": 1575.555,
        "player_2_overall_elo": 1500.851,
        "player_1_surface_elo": 1575.555,
        "player_2_surface_elo": 1500.851,
        "player_1_surface_matches": 0,
        "player_2_surface_matches": 0,
        "overall_p1_probability": 0.605881,
        "surface_p1_probability": 0.605881,
        "blended_p1_probability": 0.605881,
        "effective_overall_weight": 1.0,
        "effective_surface_weight": 0.0
      }
    }
  ]
}
