{
  "generated_at": "2026-06-08T15:00:21.693665+02:00",
  "source_url": "https://www.rezultati.com/tenis/",
  "counts": {
    "daily_scorelines": 27
  },
  "matches": [
    {
      "match_id": "",
      "match_url": "",
      "source": "rezultati_daily_results_text_fallback",
      "date": "2026-06-08",
      "player_1": "Borges N.",
      "player_2": "Atmane T.",
      "match": "Borges N. - Atmane T.",
      "winner": "Borges N.",
      "loser": "Atmane T.",
      "sets_1": 2,
      "sets_2": 0,
      "final_score": "2-0",
      "set_scores": [
        {
          "set_number": 1,
          "p1_games": 6,
          "p2_games": 4,
          "tiebreak": false
        },
        {
          "set_number": 2,
          "p1_games": 6,
          "p2_games": 4,
          "tiebreak": false
        }
      ],
      "completed": true,
      "retired": false,
      "walkover": false,
      "raw_parent_text": "Kraj\nBorges N.\nAtmane T.\n2\n0\n6\n4\n6\n4",
      "raw_header_text": "Hertogenbosch (Nizozemska), trava\nATP - SINGL:",
      "tournament": "Hertogenbosch (Nizozemska)",
      "tour_level": "atp",
      "gender": "men",
      "surface": "grass",
      "indoor": null,
      "best_of": 3,
      "is_grand_slam": false,
      "first_set_score": "6-4",
      "first_set_games": 10,
      "first_set_tiebreak": false,
      "total_games": 20,
      "p1_total_games_won": 12,
      "p2_total_games_won": 8,
      "game_margin_p1": 4,
      "total_sets": 2,
      "straight_sets": true,
      "deciding_set": false,
      "had_tiebreak": false,
      "tiebreak_count": 0
    },
    {
      "match_id": "",
      "match_url": "",
      "source": "rezultati_daily_results_text_fallback",
      "date": "2026-06-08",
      "player_1": "Bonzi B.",
      "player_2": "Rottgering M.",
      "match": "Bonzi B. - Rottgering M.",
      "winner": "Bonzi B.",
      "loser": "Rottgering M.",
      "sets_1": 2,
      "sets_2": 0,
      "final_score": "2-0",
      "set_scores": [
        {
          "set_number": 1,
          "p1_games": 6,
          "p2_games": 4,
          "tiebreak": false
        },
        {
          "set_number": 2,
          "p1_games": 6,
          "p2_games": 4,
          "tiebreak": false
        }
      ],
      "completed": true,
      "retired": false,
      "walkover": false,
      "raw_parent_text": "Kraj\nBonzi B.\nRottgering M.\n2\n0\n6\n4\n6\n4",
      "raw_header_text": "Hertogenbosch (Nizozemska), trava\nATP - SINGL:",
      "tournament": "Hertogenbosch (Nizozemska)",
      "tour_level": "atp",
      "gender": "men",
      "surface": "grass",
      "indoor": null,
      "best_of": 3,
      "is_grand_slam": false,
      "first_set_score": "6-4",
      "first_set_games": 10,
      "first_set_tiebreak": false,
      "total_games": 20,
      "p1_total_games_won": 12,
      "p2_total_games_won": 8,
      "game_margin_p1": 4,
      "total_sets": 2,
      "straight_sets": true,
      "deciding_set": false,
      "had_tiebreak": false,
      "tiebreak_count": 0
    },
    {
      "match_id": "",
      "match_url": "",
      "source": "rezultati_daily_results_text_fallback",
      "date": "2026-06-08",
      "player_1": "Davidovich Fokina A.",
      "player_2": "Bellucci M.",
      "match": "Davidovich Fokina A. - Bellucci M.",
      "winner": "Bellucci M.",
      "loser": "Davidovich Fokina A.",
      "sets_1": 1,
      "sets_2": 2,
      "final_score": "1-2",
      "set_scores": [
        {
          "set_number": 1,
          "p1_games": 2,
          "p2_games": 6,
          "tiebreak": false
        },
        {
          "set_number": 2,
          "p1_games": 7,
          "p2_games": 6,
          "tiebreak": true,
          "tiebreak_p1": 7,
          "tiebreak_p2": 5
        },
        {
          "set_number": 3,
          "p1_games": 1,
          "p2_games": 6,
          "tiebreak": false
        }
      ],
      "completed": true,
      "retired": false,
      "walkover": false,
      "raw_parent_text": "Kraj\nDavidovich Fokina A.\nBellucci M.\n1\n2\n2\n6\n7\n7\n6\n5\n1\n6",
      "raw_header_text": "Stuttgart (Njemačka), trava\nATP - SINGL:",
      "tournament": "Stuttgart (Njemačka)",
      "tour_level": "atp",
      "gender": "men",
      "surface": "grass",
      "indoor": null,
      "best_of": 3,
      "is_grand_slam": false,
      "first_set_score": "2-6",
      "first_set_games": 8,
      "first_set_tiebreak": false,
      "total_games": 28,
      "p1_total_games_won": 10,
      "p2_total_games_won": 18,
      "game_margin_p1": -8,
      "total_sets": 3,
      "straight_sets": false,
      "deciding_set": true,
      "had_tiebreak": true,
      "tiebreak_count": 1
    },
    {
      "match_id": "",
      "match_url": "",
      "source": "rezultati_daily_results_text_fallback",
      "date": "2026-06-08",
      "player_1": "Alexandrova E.",
      "player_2": "Udvardy P.",
      "match": "Alexandrova E. - Udvardy P.",
      "winner": "Udvardy P.",
      "loser": "Alexandrova E.",
      "sets_1": 0,
      "sets_2": 2,
      "final_score": "0-2",
      "set_scores": [
        {
          "set_number": 1,
          "p1_games": 4,
          "p2_games": 6,
          "tiebreak": false
        },
        {
          "set_number": 2,
          "p1_games": 6,
          "p2_games": 7,
          "tiebreak": true,
          "tiebreak_p1": 5,
          "tiebreak_p2": 7
        }
      ],
      "completed": true,
      "retired": false,
      "walkover": false,
      "raw_parent_text": "Kraj\nAlexandrova E.\nUdvardy P.\n0\n2\n4\n6\n6\n5\n7\n7",
      "raw_header_text": "S-Hertogenbosch (Nizozemska), trava\nWTA - SINGL:",
      "tournament": "S-Hertogenbosch (Nizozemska)",
      "tour_level": "wta",
      "gender": "women",
      "surface": "grass",
      "indoor": null,
      "best_of": 3,
      "is_grand_slam": false,
      "first_set_score": "4-6",
      "first_set_games": 10,
      "first_set_tiebreak": false,
      "total_games": 23,
      "p1_total_games_won": 10,
      "p2_total_games_won": 13,
      "game_margin_p1": -3,
      "total_sets": 2,
      "straight_sets": true,
      "deciding_set": false,
      "had_tiebreak": true,
      "tiebreak_count": 1
    },
    {
      "match_id": "",
      "match_url": "",
      "source": "rezultati_daily_results_text_fallback",
      "date": "2026-06-08",
      "player_1": "Linette M.",
      "player_2": "Birrell K.",
      "match": "Linette M. - Birrell K.",
      "winner": "Linette M.",
      "loser": "Birrell K.",
      "sets_1": 2,
      "sets_2": 1,
      "final_score": "2-1",
      "set_scores": [
        {
          "set_number": 1,
          "p1_games": 2,
          "p2_games": 6,
          "tiebreak": false
        },
        {
          "set_number": 2,
          "p1_games": 6,
          "p2_games": 1,
          "tiebreak": false
        },
        {
          "set_number": 3,
          "p1_games": 6,
          "p2_games": 2,
          "tiebreak": false
        }
      ],
      "completed": true,
      "retired": false,
      "walkover": false,
      "raw_parent_text": "Kraj\nLinette M.\nBirrell K.\n2\n1\n2\n6\n6\n1\n6\n2",
      "raw_header_text": "S-Hertogenbosch (Nizozemska), trava\nWTA - SINGL:",
      "tournament": "S-Hertogenbosch (Nizozemska)",
      "tour_level": "wta",
      "gender": "women",
      "surface": "grass",
      "indoor": null,
      "best_of": 3,
      "is_grand_slam": false,
      "first_set_score": "2-6",
      "first_set_games": 8,
      "first_set_tiebreak": false,
      "total_games": 23,
      "p1_total_games_won": 14,
      "p2_total_games_won": 9,
      "game_margin_p1": 5,
      "total_sets": 3,
      "straight_sets": false,
      "deciding_set": true,
      "had_tiebreak": false,
      "tiebreak_count": 0
    },
    {
      "match_id": "",
      "match_url": "",
      "source": "rezultati_daily_results_text_fallback",
      "date": "2026-06-08",
      "player_1": "Andreescu B.",
      "player_2": "Mertens E.",
      "match": "Andreescu B. - Mertens E.",
      "winner": "Mertens E.",
      "loser": "Andreescu B.",
      "sets_1": 0,
      "sets_2": 2,
      "final_score": "0-2",
      "set_scores": [
        {
          "set_number": 1,
          "p1_games": 1,
          "p2_games": 6,
          "tiebreak": false
        },
        {
          "set_number": 2,
          "p1_games": 2,
          "p2_games": 6,
          "tiebreak": false
        }
      ],
      "completed": true,
      "retired": false,
      "walkover": false,
      "raw_parent_text": "Kraj\nAndreescu B.\nMertens E.\n0\n2\n1\n6\n2\n6",
      "raw_header_text": "S-Hertogenbosch (Nizozemska), trava\nWTA - SINGL:",
      "tournament": "S-Hertogenbosch (Nizozemska)",
      "tour_level": "wta",
      "gender": "women",
      "surface": "grass",
      "indoor": null,
      "best_of": 3,
      "is_grand_slam": false,
      "first_set_score": "1-6",
      "first_set_games": 7,
      "first_set_tiebreak": false,
      "total_games": 15,
      "p1_total_games_won": 3,
      "p2_total_games_won": 12,
      "game_margin_p1": -9,
      "total_sets": 2,
      "straight_sets": true,
      "deciding_set": false,
      "had_tiebreak": false,
      "tiebreak_count": 0
    },
    {
      "match_id": "",
      "match_url": "",
      "source": "rezultati_daily_results_text_fallback",
      "date": "2026-06-08",
      "player_1": "Sachko V.",
      "player_2": "Watanuki Y.",
      "match": "Sachko V. - Watanuki Y.",
      "winner": "Sachko V.",
      "loser": "Watanuki Y.",
      "sets_1": 2,
      "sets_2": 0,
      "final_score": "2-0",
      "set_scores": [
        {
          "set_number": 1,
          "p1_games": 6,
          "p2_games": 7,
          "tiebreak": true,
          "tiebreak_p1": 2,
          "tiebreak_p2": 7
        },
        {
          "set_number": 2,
          "p1_games": 6,
          "p2_games": 4,
          "tiebreak": false
        }
      ],
      "completed": true,
      "retired": false,
      "walkover": false,
      "raw_parent_text": "Kraj\nSachko V.\nWatanuki Y.\n2\n0\n6\n2\n7\n7\n6\n4",
      "raw_header_text": "Bratislava (Slovačka), zemlja\nCHALLENGER - MUŠKI SINGL:",
      "tournament": "Bratislava (Slovačka)",
      "tour_level": "challenger",
      "gender": "",
      "surface": "clay",
      "indoor": null,
      "best_of": 3,
      "is_grand_slam": false,
      "first_set_score": "6-7",
      "first_set_games": 13,
      "first_set_tiebreak": true,
      "total_games": 23,
      "p1_total_games_won": 12,
      "p2_total_games_won": 11,
      "game_margin_p1": 1,
      "total_sets": 2,
      "straight_sets": true,
      "deciding_set": false,
      "had_tiebreak": true,
      "tiebreak_count": 1
    },
    {
      "match_id": "",
      "match_url": "",
      "source": "rezultati_daily_results_text_fallback",
      "date": "2026-06-08",
      "player_1": "Martin A.",
      "player_2": "Marti Pujolras A.",
      "match": "Martin A. - Marti Pujolras A.",
      "winner": "Martin A.",
      "loser": "Marti Pujolras A.",
      "sets_1": 2,
      "sets_2": 1,
      "final_score": "2-1",
      "set_scores": [
        {
          "set_number": 1,
          "p1_games": 6,
          "p2_games": 3,
          "tiebreak": false
        },
        {
          "set_number": 2,
          "p1_games": 4,
          "p2_games": 6,
          "tiebreak": false
        },
        {
          "set_number": 3,
          "p1_games": 6,
          "p2_games": 2,
          "tiebreak": false
        }
      ],
      "completed": true,
      "retired": false,
      "walkover": false,
      "raw_parent_text": "Kraj\nMartin A.\nMarti Pujolras A.\n2\n1\n6\n3\n4\n6\n6\n2",
      "raw_header_text": "Bratislava (Slovačka) - Kvalifikacije, zemlja\nCHALLENGER - MUŠKI SINGL:",
      "tournament": "Bratislava (Slovačka) - Kvalifikacije",
      "tour_level": "challenger",
      "gender": "",
      "surface": "clay",
      "indoor": null,
      "best_of": 3,
      "is_grand_slam": false,
      "first_set_score": "6-3",
      "first_set_games": 9,
      "first_set_tiebreak": false,
      "total_games": 27,
      "p1_total_games_won": 16,
      "p2_total_games_won": 11,
      "game_margin_p1": 5,
      "total_sets": 3,
      "straight_sets": false,
      "deciding_set": true,
      "had_tiebreak": false,
      "tiebreak_count": 0
    },
    {
      "match_id": "",
      "match_url": "",
      "source": "rezultati_daily_results_text_fallback",
      "date": "2026-06-08",
      "player_1": "Krumich M.",
      "player_2": "Erhard M.",
      "match": "Krumich M. - Erhard M.",
      "winner": "Krumich M.",
      "loser": "Erhard M.",
      "sets_1": 2,
      "sets_2": 1,
      "final_score": "2-1",
      "set_scores": [
        {
          "set_number": 1,
          "p1_games": 3,
          "p2_games": 6,
          "tiebreak": false
        },
        {
          "set_number": 2,
          "p1_games": 6,
          "p2_games": 2,
          "tiebreak": false
        },
        {
          "set_number": 3,
          "p1_games": 6,
          "p2_games": 3,
          "tiebreak": false
        }
      ],
      "completed": true,
      "retired": false,
      "walkover": false,
      "raw_parent_text": "Kraj\nKrumich M.\nErhard M.\n2\n1\n3\n6\n6\n2\n6\n3",
      "raw_header_text": "Bratislava (Slovačka) - Kvalifikacije, zemlja\nCHALLENGER - MUŠKI SINGL:",
      "tournament": "Bratislava (Slovačka) - Kvalifikacije",
      "tour_level": "challenger",
      "gender": "",
      "surface": "clay",
      "indoor": null,
      "best_of": 3,
      "is_grand_slam": false,
      "first_set_score": "3-6",
      "first_set_games": 9,
      "first_set_tiebreak": false,
      "total_games": 26,
      "p1_total_games_won": 15,
      "p2_total_games_won": 11,
      "game_margin_p1": 4,
      "total_sets": 3,
      "straight_sets": false,
      "deciding_set": true,
      "had_tiebreak": false,
      "tiebreak_count": 0
    },
    {
      "match_id": "",
      "match_url": "",
      "source": "rezultati_daily_results_text_fallback",
      "date": "2026-06-08",
      "player_1": "Neumayer L.",
      "player_2": "Daniel T.",
      "match": "Neumayer L. - Daniel T.",
      "winner": "Daniel T.",
      "loser": "Neumayer L.",
      "sets_1": 0,
      "sets_2": 2,
      "final_score": "0-2",
      "set_scores": [
        {
          "set_number": 1,
          "p1_games": 4,
          "p2_games": 6,
          "tiebreak": false
        },
        {
          "set_number": 2,
          "p1_games": 3,
          "p2_games": 6,
          "tiebreak": false
        }
      ],
      "completed": true,
      "retired": false,
      "walkover": false,
      "raw_parent_text": "Kraj\nNeumayer L.\nDaniel T.\n0\n2\n4\n6\n3\n6",
      "raw_header_text": "Bratislava (Slovačka) - Kvalifikacije, zemlja\nCHALLENGER - MUŠKI SINGL:",
      "tournament": "Bratislava (Slovačka) - Kvalifikacije",
      "tour_level": "challenger",
      "gender": "",
      "surface": "clay",
      "indoor": null,
      "best_of": 3,
      "is_grand_slam": false,
      "first_set_score": "4-6",
      "first_set_games": 10,
      "first_set_tiebreak": false,
      "total_games": 19,
      "p1_total_games_won": 7,
      "p2_total_games_won": 12,
      "game_margin_p1": -5,
      "total_sets": 2,
      "straight_sets": true,
      "deciding_set": false,
      "had_tiebreak": false,
      "tiebreak_count": 0
    },
    {
      "match_id": "",
      "match_url": "",
      "source": "rezultati_daily_results_text_fallback",
      "date": "2026-06-08",
      "player_1": "Nesterov P.",
      "player_2": "Ferrari G.",
      "match": "Nesterov P. - Ferrari G.",
      "winner": "Nesterov P.",
      "loser": "Ferrari G.",
      "sets_1": 2,
      "sets_2": 1,
      "final_score": "2-1",
      "set_scores": [
        {
          "set_number": 1,
          "p1_games": 6,
          "p2_games": 4,
          "tiebreak": false
        },
        {
          "set_number": 2,
          "p1_games": 3,
          "p2_games": 6,
          "tiebreak": false
        },
        {
          "set_number": 3,
          "p1_games": 6,
          "p2_games": 1,
          "tiebreak": false
        }
      ],
      "completed": true,
      "retired": false,
      "walkover": false,
      "raw_parent_text": "Kraj\nNesterov P.\nFerrari G.\n2\n1\n6\n4\n3\n6\n6\n1",
      "raw_header_text": "Cattolica (Italija) - Kvalifikacije, zemlja\nCHALLENGER - MUŠKI SINGL:",
      "tournament": "Cattolica (Italija) - Kvalifikacije",
      "tour_level": "challenger",
      "gender": "",
      "surface": "clay",
      "indoor": null,
      "best_of": 3,
      "is_grand_slam": false,
      "first_set_score": "6-4",
      "first_set_games": 10,
      "first_set_tiebreak": false,
      "total_games": 26,
      "p1_total_games_won": 15,
      "p2_total_games_won": 11,
      "game_margin_p1": 4,
      "total_sets": 3,
      "straight_sets": false,
      "deciding_set": true,
      "had_tiebreak": false,
      "tiebreak_count": 0
    },
    {
      "match_id": "",
      "match_url": "",
      "source": "rezultati_daily_results_text_fallback",
      "date": "2026-06-08",
      "player_1": "Ratti L.",
      "player_2": "Callejon H. S.",
      "match": "Ratti L. - Callejon H. S.",
      "winner": "Callejon H. S.",
      "loser": "Ratti L.",
      "sets_1": 1,
      "sets_2": 2,
      "final_score": "1-2",
      "set_scores": [
        {
          "set_number": 1,
          "p1_games": 6,
          "p2_games": 7,
          "tiebreak": true,
          "tiebreak_p1": 1,
          "tiebreak_p2": 7
        },
        {
          "set_number": 2,
          "p1_games": 6,
          "p2_games": 3,
          "tiebreak": false
        },
        {
          "set_number": 3,
          "p1_games": 2,
          "p2_games": 6,
          "tiebreak": false
        }
      ],
      "completed": true,
      "retired": false,
      "walkover": false,
      "raw_parent_text": "Kraj\nRatti L.\nCallejon H. S.\n1\n2\n6\n1\n7\n7\n6\n3\n2\n6",
      "raw_header_text": "Cattolica (Italija) - Kvalifikacije, zemlja\nCHALLENGER - MUŠKI SINGL:",
      "tournament": "Cattolica (Italija) - Kvalifikacije",
      "tour_level": "challenger",
      "gender": "",
      "surface": "clay",
      "indoor": null,
      "best_of": 3,
      "is_grand_slam": false,
      "first_set_score": "6-7",
      "first_set_games": 13,
      "first_set_tiebreak": true,
      "total_games": 30,
      "p1_total_games_won": 14,
      "p2_total_games_won": 16,
      "game_margin_p1": -2,
      "total_sets": 3,
      "straight_sets": false,
      "deciding_set": true,
      "had_tiebreak": true,
      "tiebreak_count": 1
    },
    {
      "match_id": "",
      "match_url": "",
      "source": "rezultati_daily_results_text_fallback",
      "date": "2026-06-08",
      "player_1": "Sanchez Jover C.",
      "player_2": "Mazza M.",
      "match": "Sanchez Jover C. - Mazza M.",
      "winner": "Sanchez Jover C.",
      "loser": "Mazza M.",
      "sets_1": 2,
      "sets_2": 1,
      "final_score": "2-1",
      "set_scores": [
        {
          "set_number": 1,
          "p1_games": 3,
          "p2_games": 6,
          "tiebreak": false
        },
        {
          "set_number": 2,
          "p1_games": 7,
          "p2_games": 6,
          "tiebreak": true,
          "tiebreak_p1": 9,
          "tiebreak_p2": 7
        },
        {
          "set_number": 3,
          "p1_games": 6,
          "p2_games": 0,
          "tiebreak": false
        }
      ],
      "completed": true,
      "retired": false,
      "walkover": false,
      "raw_parent_text": "Kraj\nSanchez Jover C.\nMazza M.\n2\n1\n3\n6\n7\n9\n6\n7\n6\n0",
      "raw_header_text": "Cattolica (Italija) - Kvalifikacije, zemlja\nCHALLENGER - MUŠKI SINGL:",
      "tournament": "Cattolica (Italija) - Kvalifikacije",
      "tour_level": "challenger",
      "gender": "",
      "surface": "clay",
      "indoor": null,
      "best_of": 3,
      "is_grand_slam": false,
      "first_set_score": "3-6",
      "first_set_games": 9,
      "first_set_tiebreak": false,
      "total_games": 28,
      "p1_total_games_won": 16,
      "p2_total_games_won": 12,
      "game_margin_p1": 4,
      "total_sets": 3,
      "straight_sets": false,
      "deciding_set": true,
      "had_tiebreak": true,
      "tiebreak_count": 1
    },
    {
      "match_id": "",
      "match_url": "",
      "source": "rezultati_daily_results_text_fallback",
      "date": "2026-06-08",
      "player_1": "Mmoh M.",
      "player_2": "Romano F.",
      "match": "Mmoh M. - Romano F.",
      "winner": "Romano F.",
      "loser": "Mmoh M.",
      "sets_1": 0,
      "sets_2": 2,
      "final_score": "0-2",
      "set_scores": [
        {
          "set_number": 1,
          "p1_games": 2,
          "p2_games": 6,
          "tiebreak": false
        },
        {
          "set_number": 2,
          "p1_games": 4,
          "p2_games": 6,
          "tiebreak": false
        }
      ],
      "completed": true,
      "retired": false,
      "walkover": false,
      "raw_parent_text": "Kraj\nMmoh M.\nRomano F.\n0\n2\n2\n6\n4\n6",
      "raw_header_text": "Ilkley (Ujedinjeno Kraljevstvo) - Kvalifikacije, trava\nCHALLENGER - MUŠKI SINGL:",
      "tournament": "Ilkley (Ujedinjeno Kraljevstvo) - Kvalifikacije",
      "tour_level": "challenger",
      "gender": "",
      "surface": "grass",
      "indoor": null,
      "best_of": 3,
      "is_grand_slam": false,
      "first_set_score": "2-6",
      "first_set_games": 8,
      "first_set_tiebreak": false,
      "total_games": 18,
      "p1_total_games_won": 6,
      "p2_total_games_won": 12,
      "game_margin_p1": -6,
      "total_sets": 2,
      "straight_sets": true,
      "deciding_set": false,
      "had_tiebreak": false,
      "tiebreak_count": 0
    },
    {
      "match_id": "",
      "match_url": "",
      "source": "rezultati_daily_results_text_fallback",
      "date": "2026-06-08",
      "player_1": "Okonkwo O.",
      "player_2": "Ghibaudo A.",
      "match": "Okonkwo O. - Ghibaudo A.",
      "winner": "Okonkwo O.",
      "loser": "Ghibaudo A.",
      "sets_1": 2,
      "sets_2": 1,
      "final_score": "2-1",
      "set_scores": [
        {
          "set_number": 1,
          "p1_games": 3,
          "p2_games": 6,
          "tiebreak": false
        },
        {
          "set_number": 2,
          "p1_games": 6,
          "p2_games": 3,
          "tiebreak": false
        },
        {
          "set_number": 3,
          "p1_games": 6,
          "p2_games": 4,
          "tiebreak": false
        }
      ],
      "completed": true,
      "retired": false,
      "walkover": false,
      "raw_parent_text": "Kraj\nOkonkwo O.\nGhibaudo A.\n2\n1\n3\n6\n6\n3\n6\n4",
      "raw_header_text": "Ilkley (Ujedinjeno Kraljevstvo) - Kvalifikacije, trava\nCHALLENGER - MUŠKI SINGL:",
      "tournament": "Ilkley (Ujedinjeno Kraljevstvo) - Kvalifikacije",
      "tour_level": "challenger",
      "gender": "",
      "surface": "grass",
      "indoor": null,
      "best_of": 3,
      "is_grand_slam": false,
      "first_set_score": "3-6",
      "first_set_games": 9,
      "first_set_tiebreak": false,
      "total_games": 28,
      "p1_total_games_won": 15,
      "p2_total_games_won": 13,
      "game_margin_p1": 2,
      "total_sets": 3,
      "straight_sets": false,
      "deciding_set": true,
      "had_tiebreak": false,
      "tiebreak_count": 0
    },
    {
      "match_id": "",
      "match_url": "",
      "source": "rezultati_daily_results_text_fallback",
      "date": "2026-06-08",
      "player_1": "Zhou Y.",
      "player_2": "Jones B.",
      "match": "Zhou Y. - Jones B.",
      "winner": "Jones B.",
      "loser": "Zhou Y.",
      "sets_1": 0,
      "sets_2": 2,
      "final_score": "0-2",
      "set_scores": [
        {
          "set_number": 1,
          "p1_games": 6,
          "p2_games": 7,
          "tiebreak": true,
          "tiebreak_p1": 7,
          "tiebreak_p2": 9
        },
        {
          "set_number": 2,
          "p1_games": 6,
          "p2_games": 7,
          "tiebreak": true,
          "tiebreak_p1": 3,
          "tiebreak_p2": 7
        }
      ],
      "completed": true,
      "retired": false,
      "walkover": false,
      "raw_parent_text": "Kraj\nZhou Y.\nJones B.\n0\n2\n6\n7\n7\n9\n6\n3\n7\n7",
      "raw_header_text": "Ilkley (Ujedinjeno Kraljevstvo) - Kvalifikacije, trava\nCHALLENGER - MUŠKI SINGL:",
      "tournament": "Ilkley (Ujedinjeno Kraljevstvo) - Kvalifikacije",
      "tour_level": "challenger",
      "gender": "",
      "surface": "grass",
      "indoor": null,
      "best_of": 3,
      "is_grand_slam": false,
      "first_set_score": "6-7",
      "first_set_games": 13,
      "first_set_tiebreak": true,
      "total_games": 26,
      "p1_total_games_won": 12,
      "p2_total_games_won": 14,
      "game_margin_p1": -2,
      "total_sets": 2,
      "straight_sets": true,
      "deciding_set": false,
      "had_tiebreak": true,
      "tiebreak_count": 2
    },
    {
      "match_id": "",
      "match_url": "",
      "source": "rezultati_daily_results_text_fallback",
      "date": "2026-06-08",
      "player_1": "Hurrion M.",
      "player_2": "Stewart H.",
      "match": "Hurrion M. - Stewart H.",
      "winner": "Stewart H.",
      "loser": "Hurrion M.",
      "sets_1": 1,
      "sets_2": 2,
      "final_score": "1-2",
      "set_scores": [
        {
          "set_number": 1,
          "p1_games": 6,
          "p2_games": 1,
          "tiebreak": false
        },
        {
          "set_number": 2,
          "p1_games": 4,
          "p2_games": 6,
          "tiebreak": false
        },
        {
          "set_number": 3,
          "p1_games": 4,
          "p2_games": 6,
          "tiebreak": false
        }
      ],
      "completed": true,
      "retired": false,
      "walkover": false,
      "raw_parent_text": "Kraj\nHurrion M.\nStewart H.\n1\n2\n6\n1\n4\n6\n4\n6",
      "raw_header_text": "Ilkley (Ujedinjeno Kraljevstvo) - Kvalifikacije, trava\nCHALLENGER - MUŠKI SINGL:",
      "tournament": "Ilkley (Ujedinjeno Kraljevstvo) - Kvalifikacije",
      "tour_level": "challenger",
      "gender": "",
      "surface": "grass",
      "indoor": null,
      "best_of": 3,
      "is_grand_slam": false,
      "first_set_score": "6-1",
      "first_set_games": 7,
      "first_set_tiebreak": false,
      "total_games": 27,
      "p1_total_games_won": 14,
      "p2_total_games_won": 13,
      "game_margin_p1": 1,
      "total_sets": 3,
      "straight_sets": false,
      "deciding_set": true,
      "had_tiebreak": false,
      "tiebreak_count": 0
    },
    {
      "match_id": "",
      "match_url": "",
      "source": "rezultati_daily_results_text_fallback",
      "date": "2026-06-08",
      "player_1": "Jorda Sanchis D.",
      "player_2": "Gulin S.",
      "match": "Jorda Sanchis D. - Gulin S.",
      "winner": "Gulin S.",
      "loser": "Jorda Sanchis D.",
      "sets_1": 0,
      "sets_2": 2,
      "final_score": "0-2",
      "set_scores": [
        {
          "set_number": 1,
          "p1_games": 2,
          "p2_games": 6,
          "tiebreak": false
        },
        {
          "set_number": 2,
          "p1_games": 3,
          "p2_games": 6,
          "tiebreak": false
        }
      ],
      "completed": true,
      "retired": false,
      "walkover": false,
      "raw_parent_text": "Kraj\nJorda Sanchis D.\nGulin S.\n0\n2\n2\n6\n3\n6",
      "raw_header_text": "Lyon (Francuska) - Kvalifikacije, zemlja\nCHALLENGER - MUŠKI SINGL:",
      "tournament": "Lyon (Francuska) - Kvalifikacije",
      "tour_level": "challenger",
      "gender": "",
      "surface": "clay",
      "indoor": null,
      "best_of": 3,
      "is_grand_slam": false,
      "first_set_score": "2-6",
      "first_set_games": 8,
      "first_set_tiebreak": false,
      "total_games": 17,
      "p1_total_games_won": 5,
      "p2_total_games_won": 12,
      "game_margin_p1": -7,
      "total_sets": 2,
      "straight_sets": true,
      "deciding_set": false,
      "had_tiebreak": false,
      "tiebreak_count": 0
    },
    {
      "match_id": "",
      "match_url": "",
      "source": "rezultati_daily_results_text_fallback",
      "date": "2026-06-08",
      "player_1": "Poullain L.",
      "player_2": "Perot R.",
      "match": "Poullain L. - Perot R.",
      "winner": "Perot R.",
      "loser": "Poullain L.",
      "sets_1": 0,
      "sets_2": 2,
      "final_score": "0-2",
      "set_scores": [
        {
          "set_number": 1,
          "p1_games": 4,
          "p2_games": 6,
          "tiebreak": false
        },
        {
          "set_number": 2,
          "p1_games": 3,
          "p2_games": 6,
          "tiebreak": false
        }
      ],
      "completed": true,
      "retired": false,
      "walkover": false,
      "raw_parent_text": "Kraj\nPoullain L.\nPerot R.\n0\n2\n4\n6\n3\n6",
      "raw_header_text": "Lyon (Francuska) - Kvalifikacije, zemlja\nCHALLENGER - MUŠKI SINGL:",
      "tournament": "Lyon (Francuska) - Kvalifikacije",
      "tour_level": "challenger",
      "gender": "",
      "surface": "clay",
      "indoor": null,
      "best_of": 3,
      "is_grand_slam": false,
      "first_set_score": "4-6",
      "first_set_games": 10,
      "first_set_tiebreak": false,
      "total_games": 19,
      "p1_total_games_won": 7,
      "p2_total_games_won": 12,
      "game_margin_p1": -5,
      "total_sets": 2,
      "straight_sets": true,
      "deciding_set": false,
      "had_tiebreak": false,
      "tiebreak_count": 0
    },
    {
      "match_id": "",
      "match_url": "",
      "source": "rezultati_daily_results_text_fallback",
      "date": "2026-06-08",
      "player_1": "Staeheli L.",
      "player_2": "Radulov I.",
      "match": "Staeheli L. - Radulov I.",
      "winner": "Staeheli L.",
      "loser": "Radulov I.",
      "sets_1": 2,
      "sets_2": 0,
      "final_score": "2-0",
      "set_scores": [
        {
          "set_number": 1,
          "p1_games": 6,
          "p2_games": 4,
          "tiebreak": false
        },
        {
          "set_number": 2,
          "p1_games": 6,
          "p2_games": 3,
          "tiebreak": false
        }
      ],
      "completed": true,
      "retired": false,
      "walkover": false,
      "raw_parent_text": "Kraj\nStaeheli L.\nRadulov I.\n2\n0\n6\n4\n6\n3",
      "raw_header_text": "Lyon (Francuska) - Kvalifikacije, zemlja\nCHALLENGER - MUŠKI SINGL:",
      "tournament": "Lyon (Francuska) - Kvalifikacije",
      "tour_level": "challenger",
      "gender": "",
      "surface": "clay",
      "indoor": null,
      "best_of": 3,
      "is_grand_slam": false,
      "first_set_score": "6-4",
      "first_set_games": 10,
      "first_set_tiebreak": false,
      "total_games": 19,
      "p1_total_games_won": 12,
      "p2_total_games_won": 7,
      "game_margin_p1": 5,
      "total_sets": 2,
      "straight_sets": true,
      "deciding_set": false,
      "had_tiebreak": false,
      "tiebreak_count": 0
    },
    {
      "match_id": "",
      "match_url": "",
      "source": "rezultati_daily_results_text_fallback",
      "date": "2026-06-08",
      "player_1": "Martineau M.",
      "player_2": "Janvier M.",
      "match": "Martineau M. - Janvier M.",
      "winner": "Martineau M.",
      "loser": "Janvier M.",
      "sets_1": 2,
      "sets_2": 1,
      "final_score": "2-1",
      "set_scores": [
        {
          "set_number": 1,
          "p1_games": 4,
          "p2_games": 6,
          "tiebreak": false
        },
        {
          "set_number": 2,
          "p1_games": 6,
          "p2_games": 3,
          "tiebreak": false
        },
        {
          "set_number": 3,
          "p1_games": 6,
          "p2_games": 4,
          "tiebreak": false
        }
      ],
      "completed": true,
      "retired": false,
      "walkover": false,
      "raw_parent_text": "Kraj\nMartineau M.\nJanvier M.\n2\n1\n4\n6\n6\n3\n6\n4",
      "raw_header_text": "Lyon (Francuska) - Kvalifikacije, zemlja\nCHALLENGER - MUŠKI SINGL:",
      "tournament": "Lyon (Francuska) - Kvalifikacije",
      "tour_level": "challenger",
      "gender": "",
      "surface": "clay",
      "indoor": null,
      "best_of": 3,
      "is_grand_slam": false,
      "first_set_score": "4-6",
      "first_set_games": 10,
      "first_set_tiebreak": false,
      "total_games": 29,
      "p1_total_games_won": 16,
      "p2_total_games_won": 13,
      "game_margin_p1": 3,
      "total_sets": 3,
      "straight_sets": false,
      "deciding_set": true,
      "had_tiebreak": false,
      "tiebreak_count": 0
    },
    {
      "match_id": "",
      "match_url": "",
      "source": "rezultati_daily_results_text_fallback",
      "date": "2026-06-08",
      "player_1": "Martinez A.",
      "player_2": "Sanchez Quilez A.",
      "match": "Martinez A. - Sanchez Quilez A.",
      "winner": "Sanchez Quilez A.",
      "loser": "Martinez A.",
      "sets_1": 0,
      "sets_2": 2,
      "final_score": "0-2",
      "set_scores": [
        {
          "set_number": 1,
          "p1_games": 2,
          "p2_games": 6,
          "tiebreak": false
        },
        {
          "set_number": 2,
          "p1_games": 3,
          "p2_games": 6,
          "tiebreak": false
        }
      ],
      "completed": true,
      "retired": false,
      "walkover": false,
      "raw_parent_text": "Kraj\nMartinez A.\nSanchez Quilez A.\n0\n2\n2\n6\n3\n6",
      "raw_header_text": "Lyon (Francuska) - Kvalifikacije, zemlja\nCHALLENGER - MUŠKI SINGL:",
      "tournament": "Lyon (Francuska) - Kvalifikacije",
      "tour_level": "challenger",
      "gender": "",
      "surface": "clay",
      "indoor": null,
      "best_of": 3,
      "is_grand_slam": false,
      "first_set_score": "2-6",
      "first_set_games": 8,
      "first_set_tiebreak": false,
      "total_games": 17,
      "p1_total_games_won": 5,
      "p2_total_games_won": 12,
      "game_margin_p1": -7,
      "total_sets": 2,
      "straight_sets": true,
      "deciding_set": false,
      "had_tiebreak": false,
      "tiebreak_count": 0
    },
    {
      "match_id": "",
      "match_url": "",
      "source": "rezultati_daily_results_text_fallback",
      "date": "2026-06-08",
      "player_1": "Castro L. C.",
      "player_2": "Cigarran T.",
      "match": "Castro L. C. - Cigarran T.",
      "winner": "Cigarran T.",
      "loser": "Castro L. C.",
      "sets_1": 0,
      "sets_2": 2,
      "final_score": "0-2",
      "set_scores": [
        {
          "set_number": 1,
          "p1_games": 4,
          "p2_games": 6,
          "tiebreak": false
        },
        {
          "set_number": 2,
          "p1_games": 2,
          "p2_games": 6,
          "tiebreak": false
        }
      ],
      "completed": true,
      "retired": false,
      "walkover": false,
      "raw_parent_text": "Kraj\nCastro L. C.\nCigarran T.\n0\n2\n4\n6\n2\n6",
      "raw_header_text": "San Miguel de Tucuman (Argentina) - Kvalifikacije, zemlja\nCHALLENGER - MUŠKI SINGL:",
      "tournament": "San Miguel de Tucuman (Argentina) - Kvalifikacije",
      "tour_level": "challenger",
      "gender": "",
      "surface": "clay",
      "indoor": null,
      "best_of": 3,
      "is_grand_slam": false,
      "first_set_score": "4-6",
      "first_set_games": 10,
      "first_set_tiebreak": false,
      "total_games": 18,
      "p1_total_games_won": 6,
      "p2_total_games_won": 12,
      "game_margin_p1": -6,
      "total_sets": 2,
      "straight_sets": true,
      "deciding_set": false,
      "had_tiebreak": false,
      "tiebreak_count": 0
    },
    {
      "match_id": "",
      "match_url": "",
      "source": "rezultati_daily_results_text_fallback",
      "date": "2026-06-08",
      "player_1": "Wang Xiy.",
      "player_2": "Samson L.",
      "match": "Wang Xiy. - Samson L.",
      "winner": "Samson L.",
      "loser": "Wang Xiy.",
      "sets_1": 0,
      "sets_2": 2,
      "final_score": "0-2",
      "set_scores": [
        {
          "set_number": 1,
          "p1_games": 6,
          "p2_games": 7,
          "tiebreak": true,
          "tiebreak_p1": 3,
          "tiebreak_p2": 7
        },
        {
          "set_number": 2,
          "p1_games": 5,
          "p2_games": 7,
          "tiebreak": false
        }
      ],
      "completed": true,
      "retired": false,
      "walkover": false,
      "raw_parent_text": "Kraj\nWang Xiy.\nSamson L.\n0\n2\n6\n3\n7\n7\n5\n7",
      "raw_header_text": "Modena (Italija), zemlja\nCHALLENGER - ŽENSKI SINGL:",
      "tournament": "Modena (Italija)",
      "tour_level": "challenger",
      "gender": "",
      "surface": "clay",
      "indoor": null,
      "best_of": 3,
      "is_grand_slam": false,
      "first_set_score": "6-7",
      "first_set_games": 13,
      "first_set_tiebreak": true,
      "total_games": 25,
      "p1_total_games_won": 11,
      "p2_total_games_won": 14,
      "game_margin_p1": -3,
      "total_sets": 2,
      "straight_sets": true,
      "deciding_set": false,
      "had_tiebreak": true,
      "tiebreak_count": 1
    },
    {
      "match_id": "",
      "match_url": "",
      "source": "rezultati_daily_results_text_fallback",
      "date": "2026-06-08",
      "player_1": "Griffiths E.",
      "player_2": "Bains N.",
      "match": "Griffiths E. - Bains N.",
      "winner": "Griffiths E.",
      "loser": "Bains N.",
      "sets_1": 2,
      "sets_2": 1,
      "final_score": "2-1",
      "set_scores": [
        {
          "set_number": 1,
          "p1_games": 2,
          "p2_games": 6,
          "tiebreak": false
        },
        {
          "set_number": 2,
          "p1_games": 7,
          "p2_games": 6,
          "tiebreak": true,
          "tiebreak_p1": 11,
          "tiebreak_p2": 9
        },
        {
          "set_number": 3,
          "p1_games": 7,
          "p2_games": 5,
          "tiebreak": false
        }
      ],
      "completed": true,
      "retired": false,
      "walkover": false,
      "raw_parent_text": "Kraj\nGriffiths E.\nBains N.\n2\n1\n2\n6\n7\n11\n6\n9\n7\n5",
      "raw_header_text": "Ilkley (Ujedinjeno Kraljevstvo) - Kvalifikacije, trava\nCHALLENGER - ŽENSKI SINGL:",
      "tournament": "Ilkley (Ujedinjeno Kraljevstvo) - Kvalifikacije",
      "tour_level": "challenger",
      "gender": "",
      "surface": "grass",
      "indoor": null,
      "best_of": 3,
      "is_grand_slam": false,
      "first_set_score": "2-6",
      "first_set_games": 8,
      "first_set_tiebreak": false,
      "total_games": 33,
      "p1_total_games_won": 16,
      "p2_total_games_won": 17,
      "game_margin_p1": -1,
      "total_sets": 3,
      "straight_sets": false,
      "deciding_set": true,
      "had_tiebreak": true,
      "tiebreak_count": 1
    },
    {
      "match_id": "",
      "match_url": "",
      "source": "rezultati_daily_results_text_fallback",
      "date": "2026-06-08",
      "player_1": "McDonald E.",
      "player_2": "Stoiber R. A.",
      "match": "McDonald E. - Stoiber R. A.",
      "winner": "McDonald E.",
      "loser": "Stoiber R. A.",
      "sets_1": 2,
      "sets_2": 0,
      "final_score": "2-0",
      "set_scores": [
        {
          "set_number": 1,
          "p1_games": 6,
          "p2_games": 2,
          "tiebreak": false
        },
        {
          "set_number": 2,
          "p1_games": 6,
          "p2_games": 4,
          "tiebreak": false
        }
      ],
      "completed": true,
      "retired": false,
      "walkover": false,
      "raw_parent_text": "Kraj\nMcDonald E.\nStoiber R. A.\n2\n0\n6\n2\n6\n4",
      "raw_header_text": "Ilkley (Ujedinjeno Kraljevstvo) - Kvalifikacije, trava\nCHALLENGER - ŽENSKI SINGL:",
      "tournament": "Ilkley (Ujedinjeno Kraljevstvo) - Kvalifikacije",
      "tour_level": "challenger",
      "gender": "",
      "surface": "grass",
      "indoor": null,
      "best_of": 3,
      "is_grand_slam": false,
      "first_set_score": "6-2",
      "first_set_games": 8,
      "first_set_tiebreak": false,
      "total_games": 18,
      "p1_total_games_won": 12,
      "p2_total_games_won": 6,
      "game_margin_p1": 6,
      "total_sets": 2,
      "straight_sets": true,
      "deciding_set": false,
      "had_tiebreak": false,
      "tiebreak_count": 0
    },
    {
      "match_id": "",
      "match_url": "",
      "source": "rezultati_daily_results_text_fallback",
      "date": "2026-06-08",
      "player_1": "Zarate C. M.",
      "player_2": "Hardt N.",
      "match": "Zarate C. M. - Hardt N.",
      "winner": "Hardt N.",
      "loser": "Zarate C. M.",
      "sets_1": 0,
      "sets_2": 2,
      "final_score": "0-2",
      "set_scores": [
        {
          "set_number": 1,
          "p1_games": 2,
          "p2_games": 6,
          "tiebreak": false
        },
        {
          "set_number": 2,
          "p1_games": 2,
          "p2_games": 6,
          "tiebreak": false
        }
      ],
      "completed": true,
      "retired": false,
      "walkover": false,
      "raw_parent_text": "Kraj\nZarate C. M.\nHardt N.\n0\n2\n2\n6\n2\n6",
      "raw_header_text": "M25 Cuiaba (Brazil), zemlja\nITF - MUŠKI SINGL:",
      "tournament": "M25 Cuiaba (Brazil)",
      "tour_level": "itf",
      "gender": "",
      "surface": "clay",
      "indoor": null,
      "best_of": 3,
      "is_grand_slam": false,
      "first_set_score": "2-6",
      "first_set_games": 8,
      "first_set_tiebreak": false,
      "total_games": 16,
      "p1_total_games_won": 4,
      "p2_total_games_won": 12,
      "game_margin_p1": -8,
      "total_sets": 2,
      "straight_sets": true,
      "deciding_set": false,
      "had_tiebreak": false,
      "tiebreak_count": 0
    }
  ]
}
